torrequests_Matikjacc/TorManager.py
torrequests_Matikjacc/__init__.py
torrequests_Matikjacc-0.0.3.dist-info/LICENSE
torrequests_Matikjacc-0.0.3.dist-info/METADATA
torrequests_Matikjacc-0.0.3.dist-info/WHEEL
torrequests_Matikjacc-0.0.3.dist-info/top_level.txt
torrequests_Matikjacc-0.0.3.dist-info/RECORD
