Metadata-Version: 2.1
Name: torrequests_Matikjacc
Version: 0.0.3
Summary: Package for making tor requests
Author-email: Matikjacc <matikjac5@gmail.com>
License: Apache License 2.0
Project-URL: Homepage, https://github.com/Matikjacc/TorRequests
Project-URL: Issues, https://github.com/Matikjacc/TorRequests/issues
Classifier: Programming Language :: Python :: 3
Classifier: License :: OSI Approved :: Apache Software License
Classifier: Operating System :: Microsoft :: Windows
Requires-Python: >=3.8
License-File: LICENSE
